devguide/__init__.py
devguide/cli.py
devguide/core.py
devguide/recommender.py
devguide/utils.py
devguide/data/__init__.py
devguide/data/projects.json
devguide/db/__init__.py
devguide/db/database.py
devguide/db/repository.py
devguide/db/schema.sql
devguide-0.3.0.dist-info/METADATA
devguide-0.3.0.dist-info/WHEEL
devguide-0.3.0.dist-info/entry_points.txt
devguide-0.3.0.dist-info/top_level.txt
devguide-0.3.0.dist-info/RECORD
