Metadata-Version: 2.4
Name: devguide
Version: 0.3.0
Requires-Dist: scikit-learn==1.4.0
Requires-Dist: rich
Requires-Dist: appdirs
Requires-Dist: stop-words
Dynamic: requires-dist
